py_de_familia/ativos-de-familia/boliviano/que-bonita.mp3
py_de_familia/ativos-de-familia/boliviano/vem-que-nem-uma-gatinha.mp3
py_de_familia/ativos-de-familia/jailson/ai-eu-nao-resisto.mp3
py_de_familia/ativos-de-familia/jailson/ai.mp3
py_de_familia/ativos-de-familia/jailson/como-assim-caralho.mp3
py_de_familia/ativos-de-familia/jailson/essa-peca-que-voce-queria.mp3
py_de_familia/ativos-de-familia/jailson/grande-e-gostosa.mp3
py_de_familia/ativos-de-familia/jailson/nao-cara.mp3
py_de_familia/ativos-de-familia/jailson/que-delicia.mp3
py_de_familia/ativos-de-familia/jailson/queimando-uma-rosquinha.mp3
py_de_familia/ativos-de-familia/jailson/tive-tanto-trabalho-para-buscar-essa-peca.mp3
py_de_familia/ativos-de-familia/jailson/trabalhando-e-relexando.mp3
py_de_familia/ativos-de-familia/kauan-desu/e-a-demora.mp3
py_de_familia/ativos-de-familia/kauan-desu/nao-vou-colocar-essa-porra-tambem-nao.mp3
py_de_familia/ativos-de-familia/pau-guina/da-cu-pra-mim.mp3
py_de_familia/ativos-de-familia/pau-guina/oco.mp3
py_de_familia/autocomplete-de-familia.sh
py_de_familia/clidefamilia.py
py_de_familia/requirements.txt
py_de_familia-0.1.3.dist-info/entry_points.txt
py_de_familia-0.1.3.dist-info/WHEEL
py_de_familia-0.1.3.dist-info/METADATA
py_de_familia-0.1.3.dist-info/RECORD
