Metadata-Version: 2.1
Name: py-de-familia
Version: 0.1.3
Summary: CLI deliciosa de família
Home-page: https://github.com/augustoliks/py-de-familia
Keywords: cli,relaxar,ai,macho
Author: augustoliks
Author-email: carlos.neto.dev@gmail.com
Maintainer: augustoliks
Maintainer-email: carlos.neto.dev@gmail.com
Requires-Python: >=3.7,<4.0
Classifier: Programming Language :: Python :: 3
Classifier: Programming Language :: Python :: 3.7
Classifier: Programming Language :: Python :: 3.8
Classifier: Programming Language :: Python :: 3.9
Classifier: Topic :: Software Development :: Libraries :: Python Modules
Requires-Dist: click (>=7.1.2,<8.0.0)
Requires-Dist: click_completion (>=0.5.2,<0.6.0)
Requires-Dist: playsound (>=1.2.2,<2.0.0)
Requires-Dist: pytest (>=6.1.2,<7.0.0)
Requires-Dist: pytest-cov (>=2.10.1,<3.0.0)
Project-URL: Documentation, https://py-de-familia.readthedocs.io/en/latest/?badge=latest
